<?xml version="1.0" encoding="UTF-8"?>

<server>

   <mbean code="org.jboss.jms.server.connectionfactory.ConnectionFactory"
          name="jboss.messaging.destination:service=ConnectionFactory,deployment=CTS"
          xmbean-dd="xmdesc/ConnectionFactory-xmbean.xml">
      <depends optional-attribute-name="ServerPeer">jboss.messaging:service=ServerPeer</depends>

      <constructor>
         <!-- default ClientID -->
         <arg type="java.lang.String" value="tck.client" />
      </constructor>

      <attribute name="JNDIBindings">
         <bindings>
            <binding>/jms/QueueConnectionFactory</binding>
            <binding>/jms/TopicConnectionFactory</binding>
            <binding>/jms/DURABLE_SUB_CONNECTION_FACTORY</binding>
            <binding>/jms/MyQueueConnectionFactory</binding>
            <binding>/jms/MyTopicConnectionFactory</binding>
         </bindings>
      </attribute>
   </mbean>

</server>
